metarank/__init__.py
metarank/client.py
metarank/schemas.py
metarank-1.1.0.dist-info/LICENSE
metarank-1.1.0.dist-info/METADATA
metarank-1.1.0.dist-info/WHEEL
metarank-1.1.0.dist-info/RECORD
