Metadata-Version: 2.1
Name: metarank
Version: 1.1.0
Summary: A Python client for metarank
License: MIT
Keywords: Recommender Systems,Metarank,ML
Author: Hannes Moser
Author-email: box@hannesmoser.at
Requires-Python: >=3.12,<4.0
Classifier: Intended Audience :: Developers
Classifier: Intended Audience :: Information Technology
Classifier: License :: OSI Approved :: MIT License
Classifier: Programming Language :: Python :: 3
Classifier: Programming Language :: Python :: 3.12
Classifier: Topic :: Software Development
Classifier: Topic :: Software Development :: Libraries
Classifier: Topic :: Software Development :: Libraries :: Python Modules
Classifier: Typing :: Typed
Requires-Dist: pydantic (>=1.7)
Requires-Dist: requests (>=2.20)
Requires-Dist: structlog (>=24.4.0,<25.0.0)
